tikup/__init__.py
tikup/argparser.py
tikup/tikup.py
tikuppppp-2021.1.20.dist-info/LICENSE
tikuppppp-2021.1.20.dist-info/METADATA
tikuppppp-2021.1.20.dist-info/WHEEL
tikuppppp-2021.1.20.dist-info/entry_points.txt
tikuppppp-2021.1.20.dist-info/top_level.txt
tikuppppp-2021.1.20.dist-info/RECORD
