Metadata-Version: 2.1
Name: tikuppppp
Version: 2021.1.20
Summary: An auto downloader and uploader for TikTok videos.
Home-page: https://github.com/Coloradohusky/TikUp
Author: Yaya
License: UNKNOWN
Platform: UNKNOWN
Requires-Python: >=3.5, <4
Requires-Dist: internetarchive (>=1.9.5)
Requires-Dist: TikTokApi (>=3.8.8)
Requires-Dist: youtube-dl (>=2020.11.12)
